ez_setup.py
randomsdss/__init__.py
randomsdss/randomsdss.py
randomsdss/data/README.md
randomsdss/data/__init__.py
randomsdss/data/dr10/DR10.BOSS.ply
randomsdss/data/dr10/DR10.SDSS.ply
randomsdss/data/dr11/DR11.BOSS.ply
randomsdss/data/dr11/DR11.SDSS.ply
randomsdss/data/dr12/DR12.BOSS.ply
randomsdss/data/dr12/DR12.SDSS.ply
randomsdss/data/dr13/DR13.SDSS.ply
randomsdss/data/dr14/DR14.LRG_N.ply
randomsdss/data/dr14/DR14.LRG_S.ply
randomsdss/data/dr14/DR14.QSO_N.ply
randomsdss/data/dr14/DR14.QSO_S.ply
randomsdss/data/dr14/DR14.SDSS.ply
randomsdss/data/dr15/DR15.SDSS.ply
randomsdss/data/dr16/DR16.SDSS.ply
randomsdss/data/dr16/DR16.eBOSS.ply
randomsdss/data/dr8/DR8.SDSS.ply
randomsdss/data/dr9/DR9.BOSS.ply
randomsdss/data/dr9/DR9.SDSS.ply
randomsdss-0.5.0.dist-info/LICENSE
randomsdss-0.5.0.dist-info/METADATA
randomsdss-0.5.0.dist-info/WHEEL
randomsdss-0.5.0.dist-info/top_level.txt
randomsdss-0.5.0.dist-info/RECORD
