Metadata-Version: 2.1
Name: randomsdss
Version: 0.5.0
Summary: Generate random points within SDSS DR8 to DR16 footprint.
Home-page: https://github.com/mchalela/RandomSDSS
Author: ['Martin Chalela']
Author-email: tinchochalela@gmail.com
License: MIT
Keywords: random,sdss,sky,pymangle,mangle
Platform: UNKNOWN
Classifier: Intended Audience :: Education
Classifier: Intended Audience :: Science/Research
Classifier: License :: OSI Approved :: MIT License
Classifier: Operating System :: OS Independent
Classifier: Programming Language :: Python
Classifier: Programming Language :: Python :: 3.9
License-File: LICENSE
Requires-Dist: attrs
Requires-Dist: numpy
Requires-Dist: pymangle
Requires-Dist: scipy
